mseep_mcp_florence2-0.3.4.dist-info/licenses/LICENSE
tests/__init__.py
tests/test_server.py
mseep_mcp_florence2-0.3.4.dist-info/METADATA
mseep_mcp_florence2-0.3.4.dist-info/WHEEL
mseep_mcp_florence2-0.3.4.dist-info/entry_points.txt
mseep_mcp_florence2-0.3.4.dist-info/top_level.txt
mseep_mcp_florence2-0.3.4.dist-info/RECORD
